minigun/__init__.py
minigun/example.py
minigun/minigun_requests.py
minigun-0.1.8.dist-info/METADATA
minigun-0.1.8.dist-info/RECORD
minigun-0.1.8.dist-info/WHEEL
minigun-0.1.8.dist-info/top_level.txt
